README.md
setup.py
iatisplit/__init__.py
iatisplit/__main__.py
iatisplit/requests_wrapper.py
iatisplit/split.py
iatisplit/version.py
iatisplit.egg-info/PKG-INFO
iatisplit.egg-info/SOURCES.txt
iatisplit.egg-info/dependency_links.txt
iatisplit.egg-info/entry_points.txt
iatisplit.egg-info/requires.txt
iatisplit.egg-info/top_level.txt