Metadata-Version: 1.0
Name: iatisplit
Version: 0.4
Summary: Split International Aid Transparency Initiative (IATI) XML activity files.
Home-page: UNKNOWN
Author:: David Megginson
Author-email:: contact@megginson.com
License: UNKNOWN
Platform: UNKNOWN
